{"updatedOn":1515421588276,"updatedBy":"admin","categories":["dataset"],"relations":[],"support":"SUPPORTED","family":"fileformat","name":"Spatial Data Transfer Standard (SDTS) ","id":"3dea4793-a568-4142-8a24-9d4c7c2c1d87","filters":[],"description":"The American National Standards Institute’s (ANSI) Spatial Data Transfer Standard (SDTS) is a mechanism for archiving and transferring spatial data (including metadata) between dissimilar computer systems. ","extras":"<?xml version=\"1.0\" encoding=\"utf-8\"?><metadata><field name=\"disclosure\">www.digitalpreservation.gov/formats/fdd/</field><field name=\"documentation\">http://webstore.ansi.org/RecordDetail.aspx?sku=ANSI+INCITS+320-1998+(R2003), http://mcmcweb.er.usgs.gov/sdts/standard.html#view, http://mcmcweb.er.usgs.gov/sdts/standard.html</field><field name=\"filenameExtension\">ddf, tar.gz</field><field name=\"internetMediaType\"></field><field name=\"pronomPUID\"></field></metadata>"}