{"family":"fileformat","extras":"<?xml version=\"1.0\" encoding=\"utf-8\"?><metadata><field name=\"disclosure\">Is open format.</field><field name=\"filenameExtension\">warc</field><field name=\"internetMediaType\"></field><field name=\"pronomPUID\"></field></metadata>","name":"WARC (Web ARChive) file format","support":"SUPPORTED","updatedBy":"admin","updatedOn":1515421588276,"description":"Web ARChive file format.  ISO 28500:2009.  Used by archival institutions to store content harvested by web crawls, for example via use of the Heritrix harvesting tool.","categories":["aggregate"],"filters":[],"relations":[{"objectType":"WEB","link":"http://www.digitalpreservation.gov/formats/fdd/","title":"Provenance information","relationType":"SPECIFIED_BY"},{"relationType":"SPECIFIED_BY","objectType":"WEB","link":"http://archive-access.sourceforge.net/warc/warc_file_format-0.9.html","title":"http://archive-access.sourceforge.net/warc/warc_file_format-0.9.html"}],"id":"88045ae8-a058-4c76-9b3b-fa952d2a0cf1"}