{"updatedOn":1515421588276,"updatedBy":"admin","categories":[],"relations":[],"id":"b72162d5-03be-4e9d-bbd6-9821bb013c2d","name":"ISO/IEC 15444-1:2004. Information technology -- JPEG 2000 image coding system -- Part 1: Core coding system [using lossless compression] (formal name); JPEG 2000 core coding, lossless compression (common name)","family":"fileformat","support":"SUPPORTED","filters":[],"description":"Lossless compression encoding generally used for full color and grayscale continuous-tone pictorial images.  ","extras":"<?xml version=\"1.0\" encoding=\"utf-8\"?><metadata><field name=\"disclosure\">www.digitalpreservation.gov/formats/fdd/</field><field name=\"documentation\"></field><field name=\"filenameExtension\"></field><field name=\"internetMediaType\"></field><field name=\"pronomPUID\"></field></metadata>"}