{"family":"fileformat","extras":"<?xml version=\"1.0\" encoding=\"utf-8\"?><metadata><field name=\"disclosure\">Is open format.</field><field name=\"filenameExtension\">xml</field><field name=\"internetMediaType\"></field><field name=\"pronomPUID\"></field></metadata>","name":"Extensible Markup Language (XML) 1.0","support":"SUPPORTED","updatedBy":"admin","updatedOn":1515421588276,"description":"Extensible Markup Language (XML) 1.0, version of XML.","categories":[],"filters":[],"relations":[{"objectType":"WEB","title":"Provenance information","link":"http://www.digitalpreservation.gov/formats/fdd/","relationType":"SPECIFIED_BY"},{"relationType":"SPECIFIED_BY","link":"http://www.w3.org/TR/xml/","title":"http://www.w3.org/TR/xml/","objectType":"WEB"},{"title":"http://www.w3.org/XML/xml-V10-4e-errata","link":"http://www.w3.org/XML/xml-V10-4e-errata","objectType":"WEB","relationType":"SPECIFIED_BY"}],"id":"dd1e605a-fad6-422f-896c-85ca4057d0c8"}