{"support":"SUPPORTED","updatedBy":"admin","name":"JPEG 2000 jp2 file format with BIIF profile 01.00 encoding","family":"fileformat","extras":"<?xml version=\"1.0\" encoding=\"utf-8\"?><metadata><field name=\"disclosure\">Is open format.</field><field name=\"filenameExtension\"></field><field name=\"internetMediaType\"></field><field name=\"pronomPUID\"></field></metadata>","relations":[{"relationType":"SPECIFIED_BY","link":"http://www.digitalpreservation.gov/formats/fdd/","title":"Provenance information","objectType":"WEB"}],"id":"f5234cd6-f137-4f77-8243-dd9ee706df39","updatedOn":1515421588276,"categories":["still-image"],"filters":[],"description":"JPEG 2000 core (part 1) wrapper containing encoded data that conforms to the BIIF profile, version 01.00"}